mqt/predictor/__init__.py
mqt/predictor/_version.py
mqt/predictor/py.typed
mqt/predictor/qcompile.py
mqt/predictor/reward.py
mqt/predictor/utils.py
mqt/predictor/hellinger/__init__.py
mqt/predictor/hellinger/utils.py
mqt/predictor/ml/__init__.py
mqt/predictor/ml/helper.py
mqt/predictor/ml/predictor.py
mqt/predictor/ml/training_data/ghz/training_data_ghz.zip
mqt/predictor/ml/training_data/trained_model/.gitkeep
mqt/predictor/ml/training_data/training_circuits/training_data_device_selection.zip
mqt/predictor/ml/training_data/training_circuits_compiled/.gitkeep
mqt/predictor/ml/training_data/training_data_aggregated/.gitkeep
mqt/predictor/rl/__init__.py
mqt/predictor/rl/actions.py
mqt/predictor/rl/helper.py
mqt/predictor/rl/parsing.py
mqt/predictor/rl/predictor.py
mqt/predictor/rl/predictorenv.py
mqt/predictor/rl/training_data/trained_model/.gitkeep
mqt/predictor/rl/training_data/training_circuits/training_data_compilation.zip
mqt_predictor-2.3.0.dist-info/METADATA
mqt_predictor-2.3.0.dist-info/WHEEL
mqt_predictor-2.3.0.dist-info/licenses/LICENSE.md
mqt_predictor-2.3.0.dist-info/RECORD
