Metadata-Version: 2.4
Name: mqt.predictor
Version: 2.3.0
Summary: MQT Predictor - A MQT Tool for Automatic Device Selection with Device-Specific Circuit Compilation for Quantum Computing
Project-URL: Homepage, https://github.com/munich-quantum-toolkit/predictor
Project-URL: Issues, https://github.com/munich-quantum-toolkit/predictor/issues
Project-URL: Discussions, https://github.com/munich-quantum-toolkit/predictor/discussions
Project-URL: Research, https://www.cda.cit.tum.de/research/quantum/
Author-email: Nils Quetschlich <nils.quetschlich@tum.de>, Lukas Burgholzer <lukas.burgholzer@tum.de>, Patrick Hopf <patrick.hopf@tum.de>
License-Expression: MIT
License-File: LICENSE.md
Keywords: MQT,compilation,machine learning,prediction,quantum computing
Classifier: Development Status :: 4 - Beta
Classifier: Intended Audience :: Developers
Classifier: Intended Audience :: Science/Research
Classifier: Natural Language :: English
Classifier: Operating System :: MacOS
Classifier: Operating System :: Microsoft :: Windows
Classifier: Operating System :: POSIX :: Linux
Classifier: Programming Language :: Python :: 3 :: Only
Classifier: Programming Language :: Python :: 3.10
Classifier: Programming Language :: Python :: 3.11
Classifier: Programming Language :: Python :: 3.12
Classifier: Programming Language :: Python :: 3.13
Classifier: Topic :: Scientific/Engineering :: Electronic Design Automation (EDA)
Requires-Python: >=3.10
Requires-Dist: bqskit>=1.2.0
Requires-Dist: mqt-bench>=2.0.0
Requires-Dist: numpy<2,>=1.22; sys_platform == 'darwin' and 'x86_64' in platform_machine and python_version < '3.13'
Requires-Dist: numpy>=1.22
Requires-Dist: numpy>=1.24; python_version >= '3.11'
Requires-Dist: numpy>=1.26; python_version >= '3.12'
Requires-Dist: numpy>=2.1; python_version >= '3.13'
Requires-Dist: pytket-qiskit>=0.60.0
Requires-Dist: pytket>=1.29.0
Requires-Dist: qiskit!=1.3.2
Requires-Dist: rich>=12.6.0
Requires-Dist: sb3-contrib>=2.0.0
Requires-Dist: scikit-learn>=1.5.1
Requires-Dist: tensorboard>=2.17.0
Requires-Dist: torch<2.3.0,>=2.2.2; sys_platform == 'darwin' and 'x86_64' in platform_machine and python_version < '3.13'
Requires-Dist: tqdm>=4.66.0
Requires-Dist: typing-extensions>=4.1
